{"My Money Blog": [{"date": "2020-03-22", "article": "Special Coronavirus Relief: Paid Leave, Mortgage Payments, Student Loans, Credit Cards, and Unemployment", "url": "https://www.mymoneyblog.com/", "new": true}], "Retire By 40": [{"date": "2020-03-22", "article": "Why Call It \u2013 The Chinese Virus?", "url": "https://retireby40.org/", "new": true}], "Oblivious Investor": [{"date": "2020-03-20", "article": "Investing Blog Roundup: Staying Healthy", "url": "https://obliviousinvestor.com/", "new": true}]}